{"[app]/IDA-External.src":{"updateexpir":1361974896118,"updatedatatype":2},"[app]/IDA-Internal.src":{"updateexpir":1361974896118,"updatedatatype":2},"[app]/IDA-Maps.src":{"updateexpir":1361974896118,"updatedatatype":2},"[app]/IDA-Person.src":{"updateexpir":1361974896119,"updatedatatype":2},"[app]/LiU-Maps.src":{"updateexpir":1361974896119,"updatedatatype":2},"[app]/LiU-Staff.src":{"updateexpir":1361974896119,"updatedatatype":2},"[app]/IDA-External.xml":{"updateexpir":1413650395821,"updatedatatype":1},"[app]/IDA-Internal.xml":{"updateexpir":1413650395822,"updatedatatype":1},"[app]/IDA-Maps.xml":{"updateexpir":1413650395823,"updatedatatype":1},"[app]/IDA-Person.xml":{"updateexpir":1413650395823,"updatedatatype":1},"[app]/LiU-Maps.xml":{"updateexpir":1413650395823,"updatedatatype":1},"[app]/LiU-Staff.xml":{"updateexpir":1413650395823,"updatedatatype":1}}